<AML>
 <Item type="Permission" id="21063B3852A2437681D4828875FE34EF" action="add">
  <is_private>0</is_private>
  <name>Preliminary sys_Function</name>
  <Relationships>
   <Item type="Access" id="19FD92AA0BAC409DBD53A38017257CE6" action="add">
    <can_change_access>1</can_change_access>
    <can_delete>0</can_delete>
    <can_discover>1</can_discover>
    <can_get>1</can_get>
    <can_update>0</can_update>
    <related_id keyed_name="Systems Engineering Manager" type="Identity">18D154535A5E4CC1A586AD227B43BC8A</related_id>
    <show_permissions_warning>0</show_permissions_warning>
    <sort_order>512</sort_order>
    <source_id keyed_name="Preliminary sys_Function" type="Permission">21063B3852A2437681D4828875FE34EF</source_id>
   </Item>
   <Item type="Access" id="3BC5A559130143C2BFAFE0EE1AD42257" action="add">
    <can_change_access>1</can_change_access>
    <can_delete>1</can_delete>
    <can_discover>1</can_discover>
    <can_get>1</can_get>
    <can_update>1</can_update>
    <related_id keyed_name="Systems Engineer" type="Identity">03DDE295D20446F6B6599B40F4CF2924</related_id>
    <show_permissions_warning>0</show_permissions_warning>
    <sort_order>128</sort_order>
    <source_id keyed_name="Preliminary sys_Function" type="Permission">21063B3852A2437681D4828875FE34EF</source_id>
   </Item>
   <Item type="Access" id="C834AFFFF7444A859F704D7D38DC7C13" action="add">
    <can_change_access>1</can_change_access>
    <can_delete>1</can_delete>
    <can_discover>1</can_discover>
    <can_get>1</can_get>
    <can_update>1</can_update>
    <related_id keyed_name="Systems Engineering Administrator" type="Identity">D35E3594A90D40C59B5B2E9777D8EBC5</related_id>
    <show_permissions_warning>0</show_permissions_warning>
    <sort_order>256</sort_order>
    <source_id keyed_name="Preliminary sys_Function" type="Permission">21063B3852A2437681D4828875FE34EF</source_id>
   </Item>
   <Item type="Access" id="EE3F1D1D953049A4AFDB999B4AB2DE1C" action="add">
    <can_change_access>0</can_change_access>
    <can_delete>0</can_delete>
    <can_discover>1</can_discover>
    <can_get>1</can_get>
    <can_update>0</can_update>
    <related_id keyed_name="Systems Engineering Consumer" type="Identity">DBDB82A32E3D42F9A23485D2955302BE</related_id>
    <show_permissions_warning>0</show_permissions_warning>
    <sort_order>384</sort_order>
    <source_id keyed_name="Preliminary sys_Function" type="Permission">21063B3852A2437681D4828875FE34EF</source_id>
   </Item>
  </Relationships>
 </Item>
</AML>